<?xml version="1.0" encoding="UTF-8"?>
<objects serializationModel="Studio.02.02.00">
	<object class="AudioFile" id="{71040cb4-1bc4-401c-a407-d80f062c6089}">
		<property name="assetPath">
			<value>pick_and_drop/drop-004.wav</value>
		</property>
		<property name="frequencyInKHz">
			<value>44.0999985</value>
		</property>
		<property name="channelCount">
			<value>2</value>
		</property>
		<property name="length">
			<value>1.1757142857142857</value>
		</property>
		<relationship name="masterAssetFolder">
			<destination>{fc5ccc50-b72f-4686-a497-cd2258164142}</destination>
		</relationship>
	</object>
</objects>
